streamlit_g2/__init__.py
streamlit_g2/spec.py
streamlit_g2/frontend/build/asset-manifest.json
streamlit_g2/frontend/build/index.html
streamlit_g2/frontend/build/static/js/2.e8b548e5.chunk.js
streamlit_g2/frontend/build/static/js/2.e8b548e5.chunk.js.LICENSE.txt
streamlit_g2/frontend/build/static/js/2.e8b548e5.chunk.js.map
streamlit_g2/frontend/build/static/js/main.d02628f0.chunk.js
streamlit_g2/frontend/build/static/js/main.d02628f0.chunk.js.map
streamlit_g2/frontend/build/static/js/runtime-main.2211e16c.js
streamlit_g2/frontend/build/static/js/runtime-main.2211e16c.js.map
streamlit_g2-0.1.1.dist-info/LICENSE
streamlit_g2-0.1.1.dist-info/METADATA
streamlit_g2-0.1.1.dist-info/WHEEL
streamlit_g2-0.1.1.dist-info/top_level.txt
streamlit_g2-0.1.1.dist-info/RECORD
