Metadata-Version: 2.1
Name: streamlit-g2
Version: 0.1.1
Summary: Render G2 charts in Streamlit
Home-page: https://github.com/hustcc/streamlit-g2
Author: hustcc
Author-email: i@hust.cc
Keywords: antv,g2,streamlit-component,streamlit-g2
Requires-Python: >=3.6
License-File: LICENSE
Requires-Dist: streamlit >=0.63
Requires-Dist: pandas >=1.0.0
Requires-Dist: simplejson
